dgad/__init__.py
dgad/api.py
dgad/cli.py
dgad/grpc/__init__.py
dgad/grpc/prediction_pb2.py
dgad/grpc/prediction_pb2_grpc.py
dgad/label_encoders/__init__.py
dgad/label_encoders/encoder_52_classes.npy
dgad/label_encoders/encoder_81_classes.npy
dgad/models/__init__.py
dgad/models/lstm_best.h5
dgad/models/tcn_best.h5
dgad/models/tcn_family_52_classes.h5
dgad/models/tcn_family_81_classes.h5
dgad/prediction.py
dgad/schema.py
dgad/utils.py
dgad-4.1.1.dist-info/entry_points.txt
dgad-4.1.1.dist-info/LICENSE
dgad-4.1.1.dist-info/WHEEL
dgad-4.1.1.dist-info/METADATA
dgad-4.1.1.dist-info/RECORD
