Metadata-Version: 2.1
Name: dgad
Version: 4.1.1
Summary: Classifies DGA domains
License: Apache-2.0
Author: Federico Falconieri
Author-email: federico.falconieri@tno.nl
Requires-Python: >=3.8,<3.11
Classifier: License :: OSI Approved :: Apache Software License
Classifier: Programming Language :: Python :: 3
Classifier: Programming Language :: Python :: 3.10
Classifier: Programming Language :: Python :: 3.8
Classifier: Programming Language :: Python :: 3.9
Requires-Dist: click (>=8.1.3,<9.0.0)
Requires-Dist: grpcio (>=1.47.0,<2.0.0)
Requires-Dist: keras-tcn (>=3.4.4,<4.0.0)
Requires-Dist: pandas (>=1.4.3,<2.0.0)
Requires-Dist: scikit-learn (>=1.1.1,<2.0.0)
Requires-Dist: tensorflow (>=2.9.1,<3.0.0)
Requires-Dist: tldextract (>=3.3.1,<4.0.0)
